stock_price/__init__.py
stock_price/stock_price.py
stock_price/💰_provider.py
stock_price-0.0.4.dist-info/METADATA
stock_price-0.0.4.dist-info/WHEEL
stock_price-0.0.4.dist-info/top_level.txt
stock_price-0.0.4.dist-info/zip-safe
stock_price-0.0.4.dist-info/RECORD
